MANIFEST.in
README.rst
buildout.cfg
requirements.txt
setup.py
version.txt
bob/__init__.py
bob.db.livdet2013.egg-info/PKG-INFO
bob.db.livdet2013.egg-info/SOURCES.txt
bob.db.livdet2013.egg-info/dependency_links.txt
bob.db.livdet2013.egg-info/entry_points.txt
bob.db.livdet2013.egg-info/not-zip-safe
bob.db.livdet2013.egg-info/requires.txt
bob.db.livdet2013.egg-info/top_level.txt
bob/db/__init__.py
bob/db/livdet2013/__init__.py
bob/db/livdet2013/driver.py
bob/db/livdet2013/models.py
bob/db/livdet2013/test.py
bob/db/livdet2013/Biometrika/test/live.txt
bob/db/livdet2013/Biometrika/test/spoof.txt
bob/db/livdet2013/Biometrika/train/live.txt
bob/db/livdet2013/Biometrika/train/spoof.txt
bob/db/livdet2013/CrossMatch/test/live.txt
bob/db/livdet2013/CrossMatch/test/spoof.txt
bob/db/livdet2013/CrossMatch/train/live.txt
bob/db/livdet2013/CrossMatch/train/spoof.txt
bob/db/livdet2013/Italdata/test/live.txt
bob/db/livdet2013/Italdata/test/spoof.txt
bob/db/livdet2013/Italdata/train/live.txt
bob/db/livdet2013/Italdata/train/spoof.txt
bob/db/livdet2013/Swipe/test/live.txt
bob/db/livdet2013/Swipe/test/spoof.txt
bob/db/livdet2013/Swipe/train/live.txt
bob/db/livdet2013/Swipe/train/spoof.txt