Metadata-Version: 1.2
Name: bob.db.livdet2013
Version: 2.1.0
Summary: LivDet 2013 Fingerprint database access for Bob
Home-page: https://gitlab.idiap.ch/bob/bob.db.livdet2013
Author: David Yambay
Author-email: yambayda@gmail.com
Maintainer: Andre Anjos
Maintainer-email: andre.anjos@idiap.ch
License: BSD
Platform: UNKNOWN
Classifier: Framework :: Bob
Classifier: Development Status :: 4 - Beta
Classifier: Intended Audience :: Developers
Classifier: License :: OSI Approved :: BSD License
Classifier: Natural Language :: English
Classifier: Programming Language :: Python
Classifier: Programming Language :: Python :: 3
Classifier: Topic :: Scientific/Engineering
Classifier: Topic :: Database :: Front-Ends
